{
  "type": "minecraft:chest",
  "pools": [
    {
      "rolls": {
        "min": 3.0,
        "max": 8.0,
        "type": "minecraft:uniform"
      },
      "entries": [
        {
          "name": "minecraft:gold_nugget",
          "type": "minecraft:item",
          "weight": 12,
          "functions": [
            {
              "function": "minecraft:set_count",
              "count": {
                "min": 4.0,
                "max": 12.0,
                "type": "minecraft:uniform"
              }
            }
          ]
        },
        {
          "name": "minecraft:netherite_scrap",
          "type": "minecraft:item",
          "weight": 1
        },
        {
          "name": "minecraft:netherite_ingot",
          "type": "minecraft:item",
          "weight": 1
        },
        {
          "name": "minecraft:diamond",
          "type": "minecraft:item",
          "weight": 4,
          "functions": [
            {
              "function": "minecraft:set_count",
              "count": {
                "min": 1.0,
                "max": 3.0,
                "type": "minecraft:uniform"
              }
            }
          ]
        },
        {
          "name": "minecraft:iron_ingot",
          "type": "minecraft:item",
          "weight": 10,
          "functions": [
            {
              "function": "minecraft:set_count",
              "count": {
                "min": 1.0,
                "max": 5.0,
                "type": "minecraft:uniform"
              }
            }
          ]
        },
        {
          "name": "minecraft:gold_ingot",
          "type": "minecraft:item",
          "weight": 12,
          "functions": [
            {
              "function": "minecraft:set_count",
              "count": {
                "min": 1.0,
                "max": 3.0,
                "type": "minecraft:uniform"
              }
            }
          ]
        },
        {
          "name": "minecraft:cooked_porkchop",
          "type": "minecraft:item",
          "weight": 15,
          "functions": [
            {
              "function": "minecraft:set_count",
              "count": {
                "min": 1.0,
                "max": 3.0,
                "type": "minecraft:uniform"
              }
            }
          ]
        },
        {
          "name": "minecraft:porkchop",
          "type": "minecraft:item",
          "weight": 15,
          "functions": [
            {
              "function": "minecraft:set_count",
              "count": {
                "min": 1.0,
                "max": 3.0,
                "type": "minecraft:uniform"
              }
            }
          ]
        },
        {
          "name": "minecraft:iron_pickaxe",
          "type": "minecraft:item",
          "weight": 5
        },
        {
          "name": "minecraft:iron_sword",
          "type": "minecraft:item",
          "weight": 5
        },
        {
          "name": "minecraft:iron_chestplate",
          "type": "minecraft:item",
          "weight": 5
        },
        {
          "name": "minecraft:iron_helmet",
          "type": "minecraft:item",
          "weight": 5
        },
        {
          "name": "minecraft:iron_leggings",
          "type": "minecraft:item",
          "weight": 5
        },
        {
          "name": "minecraft:iron_boots",
          "type": "minecraft:item",
          "weight": 5
        },
        {
          "name": "minecraft:golden_pickaxe",
          "type": "minecraft:item",
          "weight": 5
        },
        {
          "name": "minecraft:golden_sword",
          "type": "minecraft:item",
          "weight": 5
        },
        {
          "name": "minecraft:golden_chestplate",
          "type": "minecraft:item",
          "weight": 5
        },
        {
          "name": "minecraft:golden_helmet",
          "type": "minecraft:item",
          "weight": 5
        },
        {
          "name": "minecraft:golden_leggings",
          "type": "minecraft:item",
          "weight": 5
        },
        {
          "name": "minecraft:golden_boots",
          "type": "minecraft:item",
          "weight": 5
        },
        {
          "name": "minecraft:obsidian",
          "type": "minecraft:item",
          "weight": 5,
          "functions": [
            {
              "function": "minecraft:set_count",
              "count": {
                "min": 3.0,
                "max": 7.0,
                "type": "minecraft:uniform"
              }
            }
          ]
        },
        {
          "name": "minecraft:crying_obsidian",
          "type": "minecraft:item",
          "weight": 5,
          "functions": [
            {
              "function": "minecraft:set_count",
              "count": {
                "min": 3.0,
                "max": 7.0,
                "type": "minecraft:uniform"
              }
            }
          ]
        },
        {
          "name": "minecraft:crimson_fungus",
          "type": "minecraft:item",
          "weight": 5,
          "functions": [
            {
              "function": "minecraft:set_count",
              "count": {
                "min": 3.0,
                "max": 7.0,
                "type": "minecraft:uniform"
              }
            }
          ]
        },
        {
          "name": "minecraft:saddle",
          "type": "minecraft:item",
          "weight": 5
        },
        {
          "name": "minecraft:iron_horse_armor",
          "type": "minecraft:item",
          "weight": 2
        },
        {
          "name": "minecraft:golden_horse_armor",
          "type": "minecraft:item",
          "weight": 3
        },
        {
          "name": "minecraft:diamond_horse_armor",
          "type": "minecraft:item"
        }
      ]
    }
  ]
}