{
  "processors": [
    {
      "rules": [
        {
          "output_state": {
            "Name": "minecraft:lava"
          },
          "position_predicate": {
            "min_y_value": 0,
            "max_y_value": 31,
            "predicate_type": "repurposed_structures:y_value_pos_rule_test"
          },
          "input_predicate": {
            "block": "minecraft:air",
            "predicate_type": "minecraft:block_match"
          },
          "location_predicate": {
            "predicate_type": "minecraft:always_true"
          }
        }
      ],
      "processor_type": "minecraft:rule"
    },
    {
      "processor_type": "repurposed_structures:waterlogging_fix_processor"
    }
  ]
}