{
  "name": "repurposed_structures:igloos/grassy_top",
  "fallback": "minecraft:empty",
  "elements": [
    {
      "weight": 1,
      "element": {
        "location": "repurposed_structures:igloos/grassy_top",
        "processors": "repurposed_structures:igloos/grassy",
        "projection": "rigid",
        "element_type": "minecraft:single_pool_element"
      }
    },
    {
      "weight": 1,
      "element": {
        "location": "repurposed_structures:igloos/grassy_top_trapdoor",
        "processors": "repurposed_structures:igloos/grassy",
        "projection": "rigid",
        "element_type": "minecraft:single_pool_element"
      }
    }
  ]
}